exposekit/__init__.py
exposekit/proxy.py
exposekit/tunnel.py
exposekit-1.0.1.dist-info/LICENSE
exposekit-1.0.1.dist-info/METADATA
exposekit-1.0.1.dist-info/WHEEL
exposekit-1.0.1.dist-info/entry_points.txt
exposekit-1.0.1.dist-info/top_level.txt
exposekit-1.0.1.dist-info/RECORD
