Metadata-Version: 2.2
Name: exposekit
Version: 1.0.1
Summary: A library to expose localhost server to a more wider network. You can utilize this library to host your loopback server to LAN, or even the internet.
Home-page: https://github.com/pulse-empire/exposekit
Author: Pulse Empire
Author-email: Pulse Empire <nerdguy1020@gmail.com>
License: MIT
Classifier: Programming Language :: Python :: 3
Classifier: License :: OSI Approved :: MIT License
Classifier: Operating System :: OS Independent
Classifier: Development Status :: 3 - Alpha
Classifier: Intended Audience :: Developers
Classifier: License :: OSI Approved :: MIT License
Classifier: Operating System :: OS Independent
Classifier: Programming Language :: Python :: 3
Classifier: Topic :: System :: Networking
Classifier: Topic :: Software Development :: Libraries :: Python Modules
Requires-Python: >=3.7
License-File: LICENSE
Requires-Dist: requests
Dynamic: author
Dynamic: home-page
